./.env.example
./.gitignore
./.python-version
./CLAUDE.md
./LICENSE
./PKG-INFO
./README.md
./pyproject.toml
./requirements.txt
./server.py
./setup.py
./uv.lock
./config/cursor-config.json
./config/cursor-sse-config.json
metabase_fastmcp-0.1.0.dist-info/METADATA
metabase_fastmcp-0.1.0.dist-info/WHEEL
metabase_fastmcp-0.1.0.dist-info/entry_points.txt
metabase_fastmcp-0.1.0.dist-info/licenses/LICENSE
metabase_fastmcp-0.1.0.dist-info/RECORD
