Metadata-Version: 2.4
Name: metabase-fastmcp
Version: 0.1.0
Summary: Model Context Protocol (MCP) server for Metabase - Connect AI assistants like Claude and Cursor to your Metabase analytics platform
Project-URL: Homepage, https://github.com/hyeongjun-dev/metabase-mcp
Project-URL: Repository, https://github.com/hyeongjun-dev/metabase-mcp
Project-URL: Issues, https://github.com/hyeongjun-dev/metabase-mcp/issues
Author-email: cheukyin175 <cheukyin175@gmail.com>
License: MIT
License-File: LICENSE
Keywords: ai,ai-assistant,analytics,anthropic,api,automation,bi,business-intelligence,chatgpt,claude,cursor,data-analysis,database,fastmcp,llm,mcp,metabase,model-context-protocol,python,sql
Classifier: Development Status :: 4 - Beta
Classifier: Intended Audience :: Developers
Classifier: Intended Audience :: Science/Research
Classifier: Intended Audience :: System Administrators
Classifier: License :: OSI Approved :: MIT License
Classifier: Operating System :: OS Independent
Classifier: Programming Language :: Python :: 3
Classifier: Programming Language :: Python :: 3.12
Classifier: Topic :: Database
Classifier: Topic :: Office/Business
Classifier: Topic :: Scientific/Engineering :: Artificial Intelligence
Classifier: Topic :: Software Development :: Libraries :: Python Modules
Requires-Python: >=3.12
Requires-Dist: fastmcp>=0.19.0
Requires-Dist: httpx>=0.28.0
Requires-Dist: pydantic>=2.10.0
Requires-Dist: python-dotenv>=1.0.1
